Design.v
module PISO(
   input [31:0]din_i, 
   input load_i, 
   input clk_i, 
   input rst_i, 
   output reg dout_o
);

//net(s)
reg [31:0]DATA;

//PISO Register
always@(posedge clk_i) begin
   if(rst_i)
      dout_o <= 1'b0;
   else if(load_i) begin
      DATA <= din_i;
      //dout_o <= 1'b0;
   end
   else begin
      dout_o <= DATA[0];
      DATA <= {1'b0, DATA[31:1]};
   end
end


endmodule

Testbench.v
module tb_PISO();
reg load_ti;
reg clk_ti;
reg rst_ti;
reg [31:0]din_ti;
wire dout_to;

//instantiation
PISO DUT(.din_i(din_ti), 
   .load_i(load_ti), 
   .clk_i(clk_ti), 
   .rst_i(rst_ti), 
   .dout_o(dout_to));

//clock
initial begin
   clk_ti = 1'b0;
   forever
      #5 clk_ti = ~clk_ti;
end

//feeding
initial begin
rst_ti = 1'b1;
load_ti = 1'b0;
din_ti = 32'h00000000;
#10 rst_ti = 1'b0;
load_ti = 1'b1;
din_ti = 32'h84fac960;
#10 load_ti = 1'b0;
din_ti = 32'hffffffff;
#330 load_ti = 1'b1;
#10 load_ti = 1'b0;
#50 load_ti = 1'b1;
#10 $finish;
end

//capture
initial begin
$monitor("Time: %0t | Load: %b, Clk: %b | Input: %h | Output: %h", $time, load_ti, clk_ti, din_ti, dout_to);
$dumpfile("PISO.vcd");
$dumpvars(0, tb_PISO);
end
endmodule

PISO.vcd
$date
   Sat May  9 10:03:18 2026
$end

$version
  2025.2
  $dumpfile ("PISO.vcd") 
$end

$timescale
  1ps
$end

$scope module tb_PISO $end
$var reg 1 ! load_ti $end
$var reg 1 " clk_ti $end
$var reg 1 # rst_ti $end
$var reg 32 $ din_ti [31:0] $end
$var wire 1 % dout_to $end
$scope module DUT $end
$var wire 32 & din_i [31:0] $end
$var wire 1 ' load_i $end
$var wire 1 ( clk_i $end
$var wire 1 ) rst_i $end
$var reg 1 * dout_o $end
$var reg 32 + DATA [31:0] $end
$upscope $end
$upscope $end
$enddefinitions $end

#0
$dumpvars
0!
0"
1#
b0 $
x%
b0 &
0'
0(
1)
x*
bx +
$end

#5000
1"
0%
1(
0*

#10000
1!
0"
0#
b10000100111110101100100101100000 $
b10000100111110101100100101100000 &
1'
0(
0)

#15000
1"
1(
b10000100111110101100100101100000 +

#20000
0!
0"
b11111111111111111111111111111111 $
b11111111111111111111111111111111 &
0'
0(

#25000
1"
1(
b1000010011111010110010010110000 +

#30000
0"
0(

#35000
1"
1(
b100001001111101011001001011000 +

#40000
0"
0(

#45000
1"
1(
b10000100111110101100100101100 +

#50000
0"
0(

#55000
1"
1(
b1000010011111010110010010110 +

#60000
0"
0(

#65000
1"
1(
b100001001111101011001001011 +

#70000
0"
0(

#75000
1"
1%
1(
1*
b10000100111110101100100101 +

#80000
0"
0(

#85000
1"
1(
b1000010011111010110010010 +

#90000
0"
0(

#95000
1"
0%
1(
0*
b100001001111101011001001 +

#100000
0"
0(

#105000
1"
1%
1(
1*
b10000100111110101100100 +

#110000
0"
0(

#115000
1"
0%
1(
0*
b1000010011111010110010 +

#120000
0"
0(

#125000
1"
1(
b100001001111101011001 +

#130000
0"
0(

#135000
1"
1%
1(
1*
b10000100111110101100 +

#140000
0"
0(

#145000
1"
0%
1(
0*
b1000010011111010110 +

#150000
0"
0(

#155000
1"
1(
b100001001111101011 +

#160000
0"
0(

#165000
1"
1%
1(
1*
b10000100111110101 +

#170000
0"
0(

#175000
1"
1(
b1000010011111010 +

#180000
0"
0(

#185000
1"
0%
1(
0*
b100001001111101 +

#190000
0"
0(

#195000
1"
1%
1(
1*
b10000100111110 +

#200000
0"
0(

#205000
1"
0%
1(
0*
b1000010011111 +

#210000
0"
0(

#215000
1"
1%
1(
1*
b100001001111 +

#220000
0"
0(

#225000
1"
1(
b10000100111 +

#230000
0"
0(

#235000
1"
1(
b1000010011 +

#240000
0"
0(

#245000
1"
1(
b100001001 +

#250000
0"
0(

#255000
1"
1(
b10000100 +

#260000
0"
0(

#265000
1"
0%
1(
0*
b1000010 +

#270000
0"
0(

#275000
1"
1(
b100001 +

#280000
0"
0(

#285000
1"
1%
1(
1*
b10000 +

#290000
0"
0(

#295000
1"
0%
1(
0*
b1000 +

#300000
0"
0(

#305000
1"
1(
b100 +

#310000
0"
0(

#315000
1"
1(
b10 +

#320000
0"
0(

#325000
1"
1(
b1 +

#330000
0"
0(

#335000
1"
1%
1(
1*
b0 +

#340000
0"
0(

#345000
1"
0%
1(
0*

#350000
1!
0"
1'
0(

#355000
1"
1(
b11111111111111111111111111111111 +

#360000
0!
0"
0'
0(

#365000
1"
1%
1(
1*
b1111111111111111111111111111111 +

#370000
0"
0(

#375000
1"
1(
b111111111111111111111111111111 +

#380000
0"
0(

#385000
1"
1(
b11111111111111111111111111111 +

#390000
0"
0(

#395000
1"
1(
b1111111111111111111111111111 +

#400000
0"
0(

#405000
1"
1(
b111111111111111111111111111 +

#410000
1!
0"
1'
0(

#415000
1"
1(
b11111111111111111111111111111111 +
